{
  "domain": "trace.com",
  "channel_name": "trace",
  "chaincode_name": "dairy",
  "chaincode_version": "1.5",
  "orderer": {
    "orderer_name": "orderer0",
    "port": "7050"
  },
  "endorse": "AND ('OrgDairyMSP.member')",
  "cli_name": "cli",
  "chaincode_orgs": [
    {
      "org_name": "OrgDairy",
      "peers": [
        {
          "peer_name": "peer0",
          "port": "7051"
        },
        {
          "peer_name": "peer1",
          "port": "8051"
        }
      ]
    },
    {
      "org_name": "OrgSell",
      "peers": [
        {
          "peer_name": "peer0",
          "port": "11051"
        },
        {
          "peer_name": "peer1",
          "port": "12051"
        }
      ]
    }
  ]
}
